aiopaypaythonwebapi/__init__.py
aiopaypaythonwebapi/main.py
aiopaypaython_webapi-3.0.0.dist-info/METADATA
aiopaypaython_webapi-3.0.0.dist-info/WHEEL
aiopaypaython_webapi-3.0.0.dist-info/top_level.txt
aiopaypaython_webapi-3.0.0.dist-info/RECORD
