Metadata-Version: 2.2
Name: aiopaypaython-webapi
Version: 3.0.0
Summary: Paypay WebAPI wrapper for asyncio
Author-email: nennneko5787 <h4369@nennneko5787.net>
Project-URL: Homepage, https://github.com/nennneko5787/aiopaypaython-webapi
Project-URL: Issues, https://github.com/nennneko5787/aiopaypaython-webapi/issues
Classifier: Programming Language :: Python :: 3
Classifier: License :: OSI Approved :: GNU Affero General Public License v3
Classifier: Operating System :: OS Independent
Classifier: Natural Language :: Japanese
Requires-Python: >=3.8
Requires-Dist: httpx
Requires-Dist: build
Requires-Dist: twine
